protlib.py
ecmind_protlib_transition-1.5.0.dist-info/LICENSE.txt
ecmind_protlib_transition-1.5.0.dist-info/METADATA
ecmind_protlib_transition-1.5.0.dist-info/WHEEL
ecmind_protlib_transition-1.5.0.dist-info/top_level.txt
ecmind_protlib_transition-1.5.0.dist-info/RECORD
