Metadata-Version: 2.1
Name: ecmind-protlib-transition
Version: 1.5.0
Summary: library for implementing binary network protocols
Home-page: https://github.com/rolandkoller/protlib
Author: Eli Courtwright
Author-email: eli@courtwright.org
License: BSD
Platform: UNKNOWN
Classifier: Programming Language :: Python
Classifier: Programming Language :: Python :: 3
Classifier: License :: OSI Approved :: BSD License
Classifier: Operating System :: OS Independent
Classifier: Development Status :: 5 - Production/Stable
Classifier: Intended Audience :: Developers
Classifier: Topic :: Software Development :: Libraries :: Python Modules
Classifier: Topic :: System :: Networking
License-File: LICENSE.txt
